arrlio/__init__.py
arrlio/backends/__init__.py
arrlio/backends/base.py
arrlio/backends/local.py
arrlio/backends/rabbitmq.py
arrlio/configs.py
arrlio/core.py
arrlio/exceptions.py
arrlio/executor.py
arrlio/models.py
arrlio/plugins/__init__.py
arrlio/plugins/base.py
arrlio/plugins/events.py
arrlio/plugins/graphs.py
arrlio/serializers/__init__.py
arrlio/serializers/base.py
arrlio/serializers/json.py
arrlio/serializers/msgpack.py
arrlio/serializers/nop.py
arrlio/settings.py
arrlio/types.py
arrlio/utils.py
arrlio-0.24.0.dist-info/LICENSE
arrlio-0.24.0.dist-info/METADATA
arrlio-0.24.0.dist-info/WHEEL
arrlio-0.24.0.dist-info/RECORD
