Metadata-Version: 2.1
Name: arrlio
Version: 0.24.0
Summary: 
License: MIT
Keywords: rabbitmq
Author: Roman Koshel
Author-email: roma.koshel@gmail.com
Requires-Python: >=3.10,<4.0
Classifier: Development Status :: 3 - Alpha
Classifier: License :: OSI Approved :: MIT License
Classifier: Programming Language :: Python
Classifier: Programming Language :: Python :: 3
Classifier: Programming Language :: Python :: 3.10
Classifier: Programming Language :: Python :: 3.11
Classifier: Programming Language :: Python :: 3 :: Only
Classifier: Topic :: Software Development :: Libraries :: Python Modules
Classifier: Topic :: Utilities
Requires-Dist: aiormq (>=6.7.6)
Requires-Dist: msgpack
Requires-Dist: pydantic (>=2,<3)
Requires-Dist: pydantic_settings
Requires-Dist: rich
Requires-Dist: roview
Requires-Dist: yarl
